MikkUtils/__init__.py
MikkUtils-0.0.4.dist-info/LICENCE.txt
MikkUtils-0.0.4.dist-info/METADATA
MikkUtils-0.0.4.dist-info/WHEEL
MikkUtils-0.0.4.dist-info/top_level.txt
MikkUtils-0.0.4.dist-info/RECORD
