Metadata-Version: 2.1
Name: MikkUtils
Version: 0.0.4
Summary: Utilities for scripting in my projects, almost is goldsource-related
Home-page: https://github.com/Mikk155/MikkUtils
Author: Mikk155
Author-email: 
Classifier: Programming Language :: Python :: 3
Classifier: License :: OSI Approved :: MIT License
Classifier: Operating System :: OS Independent
Requires-Python: >=3.11
License-File: LICENCE.txt
